{
    "status": "ok",
    "totalResults": 19,
    "articles": [
        {
            "source": {
                "id": null,
                "name": "Hindustan Times"
            },
            "author": "HT Sports Desk",
            "title": "Ashwin quotes MS Dhoni after Hardik's ‘doesn’t matter' remark on loss to Windies - Hindustan Times",
            "description": "Ashwin did not take Hardik's name but he quoted legendary India MS Dhoni to share an important lesson after India's T20I series loss to West Indies. | Cricket",
            "url": "https://www.hindustantimes.com/cricket/ashwin-quotes-ms-dhoni-after-hardik-pandyas-doesn-t-matter-remark-on-t20i-series-loss-to-west-indies-101692112065582.html",
            "urlToImage": "https://www.hindustantimes.com/ht-img/img/2023/08/15/1600x900/cricket-wc-2019-ind-afg_805413aa-958d-11e9-af8a-d24c1464451a_1692112301647.jpg",
            "publishedAt": "2023-08-16T00:54:46Z",
            "content": "Social media can be harsh. Neither does it take time to form an opinion, nor to change it with the wink of an aye. India T20I captain Hardik Pandya is the latest victim of it in Indian cricket. The a… [+2973 chars]"
        },
        {
            "source": {
                "id": null,
                "name": "Hindustan Times"
            },
            "author": "PTI",
            "title": "PCB issues show-cause notice to Pakistan players in USA - Hindustan Times",
            "description": "The PCB has acted after Test player Fawad Alam moved to the USA to play cricket and with the eventual aim of settling down in the country. | Cricket",
            "url": "https://www.hindustantimes.com/cricket/pcb-issues-show-cause-notice-to-pakistan-players-in-usa-101692121501896.html",
            "urlToImage": "https://www.hindustantimes.com/ht-img/img/2023/08/15/1600x900/AP07-27-2023-000355B-0_1692121753545_1692121780324.jpg",
            "publishedAt": "2023-08-15T17:55:43Z",
            "content": "The Pakistan Cricket Board has issued show-cause notices to its players participating in the minor leagues in the USA without obtaining the mandatory no-objection certificate (NOCs). The PCB has acte… [+2573 chars]"
        },
        {
            "source": {
                "id": null,
                "name": "Cricket.one"
            },
            "author": "Shivani Shukla",
            "title": "CPL 2023 | Live Streaming Channel, Squads, Fixture, Date & Time - OneCricket",
            "description": "The tournament will be played in a round-robin format.",
            "url": "https://cricket.one/cricket-news/cpl-2023-live-streaming-channel-squads-fixture-date-time/64db92f02de204fe83c13e52",
            "urlToImage": "https://ik.imagekit.io/c7syb8qpjp/oc/oc-dashboard/news-images-prod/1692079645553_CPL-2023-to-see-one-of-its-kind-red-card-like-rule.webp",
            "publishedAt": "2023-08-15T15:15:56Z",
            "content": "CPL 2023 is set to kick off on August 17 | Source: Twitter  The 11th edition of the Caribbean Premier League (CPL) is set to kick off on August 17, with the tournament's final scheduled to be played… [+2764 chars]"
        },
        {
            "source": {
                "id": null,
                "name": "OpIndia"
            },
            "author": "OpIndia Staff",
            "title": "Virat Kohli calls out Times of India for publishing fake news about him building a cricket pitch in his new Alibaug farmhouse - OpIndia",
            "description": "Virat Kohli took to Instagram to slam the Times of India for publishing 'fake news' about his plans to build a cricket pitch inside his farmhouse in Alibaug | OpIndia News",
            "url": "https://www.opindia.com/2023/08/virat-kohli-slams-times-of-india-for-publishing-fake-news-on-alibaug-farmhouse/",
            "urlToImage": "https://www.opindia.com/wp-content/uploads/2023/08/Virat-Anushka.jpg",
            "publishedAt": "2023-08-15T15:15:45Z",
            "content": "On Tuesday, August 14, Virat Kohli slammed the Times of India for publishing ‘fake news’ about his plans to build a cricket pitch inside his farmhouse in Alibaug, which is being constructed at the mo… [+2750 chars]"
        },
        {
            "source": {
                "id": null,
                "name": "NDTV News"
            },
            "author": "NDTV Sports Desk",
            "title": "'Hi Date...': Yuzvendra Chahal's Message For Wife Dhanashree Verma Goes Viral - NDTV Sports",
            "description": "Indian cricket team star Yuzvendra Chahal and his wife Dhanashree Verma, who is a very popular social media personality, are a power couple",
            "url": "https://sports.ndtv.com/cricket/hi-date-yuzvendra-chahals-message-for-wife-dhanashree-verma-goes-viral-4299233",
            "urlToImage": "https://c.ndtvimg.com/2023-08/vgpb40uo_chahal-dhanashree_625x300_15_August_23.jpg",
            "publishedAt": "2023-08-15T14:44:36Z",
            "content": "Indian cricket team star Yuzvendra Chahal and his wife Dhanashree Verma, who is a very popular social media personality, are a power couple. They can often sharing viral posts on social media. Chahal… [+1950 chars]"
        },
        {
            "source": {
                "id": null,
                "name": "Hindustan Times"
            },
            "author": "HT Sports Desk",
            "title": "‘It seems Buttler's duty is to watch Ben Stokes': Ashwin on retirement U-Turn - Hindustan Times",
            "description": "Ashwin said Buttler, his teammate at the Rajasthan Royals, is a man of few words and he will try his best to convince Stokes to come out of ODI retirement. | Cricket",
            "url": "https://www.hindustantimes.com/cricket/it-seems-jos-buttlers-duty-is-to-watch-ben-stokes-ashwin-on-retirement-u-turns-in-english-cricket-101692108548700.html",
            "urlToImage": "https://www.hindustantimes.com/ht-img/img/2023/08/15/1600x900/Screenshot_2023-08-15_194257_1692108797033_1692108819874.png",
            "publishedAt": "2023-08-15T14:16:37Z",
            "content": "India all-rounder Ravichandran Ashwin reacted to reports in the British media about England Test captain Ben Stokes' possible U-Turn on ODI retirement to play the World Cup in India later this year. … [+2965 chars]"
        },
        {
            "source": {
                "id": "the-times-of-india",
                "name": "The Times of India"
            },
            "author": "TIMESOFINDIA.COM",
            "title": "'Pakistan have..., India don't...': Former Pak player on Asia Cup clash - IndiaTimes",
            "description": "Cricket News: India hold the upper hand over Pakistan in the recent past and emerged victorious in the multi-team events barring their loss in 2021 T20 World Cup. B",
            "url": "https://timesofindia.indiatimes.com/sports/cricket/asia-cup/pakistan-have-india-dont-former-pak-player-on-asia-cup-clash/articleshow/102749834.cms",
            "urlToImage": "https://static.toiimg.com/thumb/msid-102749831,width-1070,height-580,imgsize-59080,resizemode-75,overlay-toi_sw,pt-32,y_pad-40/photo.jpg",
            "publishedAt": "2023-08-15T13:19:00Z",
            "content": null
        },
        {
            "source": {
                "id": "the-times-of-india",
                "name": "The Times of India"
            },
            "author": "TIMESOFINDIA.COM",
            "title": "India vs Pakistan World Cup match ticket sales to start from September. Find out more details - IndiaTimes",
            "description": "Cricket News: The International Cricket Council (ICC) on Tuesday announced their plan for the sale of tickets for the upcoming ODI World Cup 2023, set to commence i",
            "url": "https://timesofindia.indiatimes.com/sports/cricket/icc-world-cup/india-vs-pakistan-world-cup-match-ticket-sales-to-start-from-september-find-out-more-details/articleshow/102749567.cms",
            "urlToImage": "https://static.toiimg.com/thumb/msid-102749536,width-1070,height-580,imgsize-92728,resizemode-75,overlay-toi_sw,pt-32,y_pad-40/photo.jpg",
            "publishedAt": "2023-08-15T13:01:00Z",
            "content": null
        },
        {
            "source": {
                "id": "espn-cric-info",
                "name": "ESPN Cric Info"
            },
            "author": "ESPNcricinfo staff",
            "title": "England to host Zimbabwe for one-off four-day Test in May 2025 - ESPNcricinfo",
            "description": "They have not played a bilateral series against each other in any format since 2004, with cricketing relations severed at one point due to political issues",
            "url": "https://www.espncricinfo.com/story/england-to-host-zimbabwe-for-one-off-four-day-test-in-may-2025-1392600",
            "urlToImage": "https://img1.hscicdn.com/image/upload/f_auto/lsci/db/PICTURES/CMS/365600/365658.6.jpg",
            "publishedAt": "2023-08-15T10:00:02Z",
            "content": "England have not played Zimbabwe in a Test since 2003, when James Anderson made his debut  •  PA Photos"
        },
        {
            "source": {
                "id": null,
                "name": "Cricket.one"
            },
            "author": "Robin",
            "title": "Cricket Fantasy Predictions Today | The Hundred 2023, Match 21 | OVI vs LON - Cricket Exchange Fantasy Teams - OneCricket",
            "description": "Fantasy tips and teams for the 21st Match of The Hundred 2023 Men's.",
            "url": "https://cricket.one/fantasy-analysis/cricket-fantasy-predictions-today-the-hundred-2023-match-21-ovi-vs-lon-cricket-exchange-fantasy-teams/64db4a28ee9b3134f4a63e1c",
            "urlToImage": "https://ik.imagekit.io/c7syb8qpjp/oc/oc-dashboard/news-images-prod/1692092963984_OVI.jpeg",
            "publishedAt": "2023-08-15T09:51:48Z",
            "content": "OVI vs LON, The Hundred 2023 Men's: Cricket Fantasy Tips and Teams for the 21st Match (Source: Twitter) Oval Invincibles (OVI) and London Spirit (LON) will lock horns against each other in the 21st … [+4573 chars]"
        },
        {
            "source": {
                "id": null,
                "name": "Hindustan Times"
            },
            "author": "HT Sports Desk",
            "title": "PCB 'shamed' for snubbing Imran Khan from Pakistan cricket's documentary - Hindustan Times",
            "description": "The video faced sever backlash across all social media platforms over the exclusion of Imran Khan, the captain of 1992 World Cup, from the celebratory video. | Cricket",
            "url": "https://www.hindustantimes.com/cricket/absolutely-disgusting-new-low-each-day-pcb-shamed-for-snubbing-imran-khan-from-pakistan-crickets-documentary-101692087288879.html",
            "urlToImage": "https://www.hindustantimes.com/ht-img/img/2023/08/15/1600x900/pak_cricket_doicu_1692087854324_1692087865286.jpg",
            "publishedAt": "2023-08-15T09:01:46Z",
            "content": "On the 76th Independence Day of Pakistan, the Pakistan Cricket Board (PCB) released a heartfelt documentary video on social media which featured some of the legends of the sport and their priceless c… [+2245 chars]"
        },
        {
            "source": {
                "id": null,
                "name": "International Cricket Council"
            },
            "author": "ICC",
            "title": "ICC Women's Player of the Month for July 2023 revealed - ICC Cricket",
            "description": "Australia's star all-rounder becomes the first-ever player – male or female – to win the ICC Player of the Month Award in consecutive months.",
            "url": "https://www.icc-cricket.com/news/3626552",
            "urlToImage": "https://resources.pulse.icc-cricket.com/ICC/photo/2023/08/15/2e17ef06-1fa6-4639-8791-066f0cbc43b9/ash1.jpg",
            "publishedAt": "2023-08-15T08:05:36Z",
            "content": "Australia's star all-rounder becomes the first-ever player male or female to win the ICC Player of the Month Award in consecutive months.There's no stopping Ashleigh Gardner at the moment after the A… [+2538 chars]"
        },
        {
            "source": {
                "id": null,
                "name": "Business Standard"
            },
            "author": "Business Standard",
            "title": "HCLTech announces new digital transformation deal from Cricket Australia - Business Standard",
            "description": null,
            "url": "https://www.business-standard.com/companies/news/hcltech-announces-new-digital-transformation-deal-from-cricket-australia-123081500281_1.html",
            "urlToImage": null,
            "publishedAt": "2023-08-15T07:57:02Z",
            "content": null
        },
        {
            "source": {
                "id": null,
                "name": "Yo Vizag"
            },
            "author": "Team Yo! Vizag",
            "title": "Andhra Premier League Season 2 schedule: 19 matches to entertain Vizag for two weeks - Yo Vizag",
            "description": "Below is the schedule of Andhra Premier League Season 2 happening in Vizag from Wednesday, 16 August 2023, at Dr YSR ACA-VDCA Cricket Stadium",
            "url": "https://www.yovizag.com/andhra-premier-league-season-2-schedule-19-matches-to-entertain-vizag-for-two-weeks/",
            "urlToImage": "https://www.yovizag.com/wp-content/uploads/2023/08/jpg_20230727_132107_0000.jpg",
            "publishedAt": "2023-08-15T06:28:15Z",
            "content": "Season 2 of Andhra Premier League (APL), the state’s very own T20 cricket league, is set to kickstart on Wednesday, 16 August 2023, at the Dr YSR ACA-VDCA International Cricket Stadium in Vizag. Afte… [+1151 chars]"
        },
        {
            "source": {
                "id": null,
                "name": "International Cricket Council"
            },
            "author": "ICC",
            "title": "Sri Lanka all-rounder retires from Test cricket - ICC Cricket",
            "description": "Sri Lanka bowling all-rounder Wanindu Hasaranga retires from Test cricket to extend his limited-overs playing career.",
            "url": "https://www.icc-cricket.com/news/3635187",
            "urlToImage": "https://resources.pulse.icc-cricket.com/ICC/photo/2023/08/15/107cc666-d9d3-4f60-84f0-da53ac43cfad/GettyImages-1241278226.jpg",
            "publishedAt": "2023-08-15T06:25:24Z",
            "content": "Sri Lanka bowling all-rounder Wanindu Hasaranga retires from Test cricket to extend his limited-overs playing career.Hasaranga, 26, made his Test debut in December 2020 against South Africa, and sinc… [+1005 chars]"
        },
        {
            "source": {
                "id": "the-times-of-india",
                "name": "The Times of India"
            },
            "author": "TIMESOFINDIA.COM",
            "title": "Watch: Prasidh Krishna grabs a wicket on his comeback - IndiaTimes",
            "description": "Cricket News: Gearing up for the T20I series against Ireland, Prasidh Krishna grabbed a wicket continuing his comeback to competitive cricket in Bengaluru on Sunday",
            "url": "https://timesofindia.indiatimes.com/sports/cricket/news/watch-prasidh-krishna-grabs-a-wicket-on-his-comeback/articleshow/102740464.cms",
            "urlToImage": "https://static.toiimg.com/thumb/msid-102740420,width-1070,height-580,imgsize-27026,resizemode-75,overlay-toi_sw,pt-32,y_pad-40/photo.jpg",
            "publishedAt": "2023-08-15T05:06:00Z",
            "content": null
        },
        {
            "source": {
                "id": null,
                "name": "NDTV News"
            },
            "author": "NDTV Sports Desk",
            "title": "Watch: Indian Cricket Team Great MS Dhoni Rides Honda Repsol 150 In Ranchi, Video Goes Viral - NDTV Sports",
            "description": "A video of former India captain MS Dhoni is going viral on social media in which the Jharkhand-born cricketer could be seen riding a motorbike in Ranchi.",
            "url": "https://sports.ndtv.com/cricket/ms-dhoni-rides-honda-repsol-150-in-ranchi-video-goes-viral-watch-4297519",
            "urlToImage": "https://c.ndtvimg.com/2023-08/vdl1mano_ms-dhoni-instagram_625x300_14_August_23.jpg",
            "publishedAt": "2023-08-15T03:34:00Z",
            "content": "A video of former India captain MS Dhoni is going viral on social media in which the Jharkhand-born cricketer could be seen riding his motorbike Honda Repsol 150 in Ranchi. The clip has Dhoni in comp… [+1274 chars]"
        },
        {
            "source": {
                "id": null,
                "name": "Hindustan Times"
            },
            "author": "Reuters",
            "title": "South Africa select batting talent 'Baby AB' Brevis for Australia series - Hindustan Times",
            "description": "Dewald Brevis has the highest score in South Africa’s domestic T20 cricket with 162 from 57 balls.  | Cricket",
            "url": "https://www.hindustantimes.com/cricket/south-africa-select-batting-talent-baby-ab-brevis-for-australia-series-ahead-of-odi-world-cup-101692033609735.html",
            "urlToImage": "https://www.hindustantimes.com/ht-img/img/2023/08/14/1600x900/FKsoFCkXwAgbRdM_1_1692033719021_1692033719159.jpg",
            "publishedAt": "2023-08-14T17:23:09Z",
            "content": "South Africa have included precocious batting talent Dewald Brevis in their One-Day and Twenty20 International squads for their eight-match limited-overs home series against Australia starting later … [+2043 chars]"
        },
        {
            "source": {
                "id": "the-times-of-india",
                "name": "The Times of India"
            },
            "author": "TIMESOFINDIA.COM",
            "title": "IND vs WI 5th T20I: WATCH - Tilak Varma claims maiden international wicket and his victim is.... - IndiaTimes",
            "description": "Cricket News: Not only did Tilak Varma impress with his batting in his debut international series, but he also stole the limelight by claiming his first internation",
            "url": "https://timesofindia.indiatimes.com/sports/cricket/india-in-west-indies/ind-vs-wi-5th-t20i-watch-tilak-varma-claims-maiden-international-wicket/articleshow/102707459.cms",
            "urlToImage": "https://static.toiimg.com/thumb/msid-102707500,width-1070,height-580,imgsize-62094,resizemode-75,overlay-toi_sw,pt-32,y_pad-40/photo.jpg",
            "publishedAt": "2023-08-14T02:50:00Z",
            "content": null
        }
    ]
}